[
    {
        "Id": 301,
        "GachaStampSheetGroupId": 10003,
        "GachaStampSheetSeq": 1,
        "StampCount": 6,
        "DefaultGachaStampSheetCellChoiceId": 30101
    },
    {
        "Id": 302,
        "GachaStampSheetGroupId": 10003,
        "GachaStampSheetSeq": 1,
        "StampCount": 12,
        "DefaultGachaStampSheetCellChoiceId": 30201
    },
    {
        "Id": 303,
        "GachaStampSheetGroupId": 10003,
        "GachaStampSheetSeq": 2,
        "StampCount": 12,
        "DefaultGachaStampSheetCellChoiceId": 30302
    },
    {
        "Id": 304,
        "GachaStampSheetGroupId": 10003,
        "GachaStampSheetSeq": 3,
        "StampCount": 12,
        "DefaultGachaStampSheetCellChoiceId": 30402
    }
]