{
    "data": [
        {
            "id": 2,
            "value": ""
        },
        {
            "id": 851000000002002,
            "value": "鉄巨人討伐"
        },
        {
            "id": 851000000002003,
            "value": "ヘルハウス討伐"
        },
        {
            "id": 851000000003005,
            "value": "セフィロス降臨"
        },
        {
            "id": 851000000003008,
            "value": "ゴールドボムラッシュ"
        },
        {
            "id": 863000002002001,
            "value": "鉄巨人"
        },
        {
            "id": 863000002003001,
            "value": "ヘルハウス"
        },
        {
            "id": 863000002004001,
            "value": "リベンジウォーズ"
        },
        {
            "id": 863000002005001,
            "value": "セフィロス"
        },
        {
            "id": 863000003005001,
            "value": "セフィロス"
        }
    ]
}